{
  "parent": "minecraft:block/thin_block",
  "overrides": [
    {
      "model": "domum_ornamentum:block/panel/panel_full_spec",
      "predicate": {
        "domum_ornamentum:trapdoor_type": 0.0
      }
    },
    {
      "model": "domum_ornamentum:block/panel/panel_horizontally_squiggly_striped_spec",
      "predicate": {
        "domum_ornamentum:trapdoor_type": 1.0
      }
    },
    {
      "model": "domum_ornamentum:block/panel/panel_horizontally_striped_spec",
      "predicate": {
        "domum_ornamentum:trapdoor_type": 2.0
      }
    },
    {
      "model": "domum_ornamentum:block/panel/panel_port_manteau_spec",
      "predicate": {
        "domum_ornamentum:trapdoor_type": 3.0
      }
    },
    {
      "model": "domum_ornamentum:block/panel/panel_vertically_squiggly_striped_spec",
      "predicate": {
        "domum_ornamentum:trapdoor_type": 4.0
      }
    },
    {
      "model": "domum_ornamentum:block/panel/panel_vertically_striped_spec",
      "predicate": {
        "domum_ornamentum:trapdoor_type": 5.0
      }
    },
    {
      "model": "domum_ornamentum:block/panel/panel_waffle_spec",
      "predicate": {
        "domum_ornamentum:trapdoor_type": 6.0
      }
    },
    {
      "model": "domum_ornamentum:block/panel/panel_slot_spec",
      "predicate": {
        "domum_ornamentum:trapdoor_type": 7.0
      }
    }
  ]
}